documente_shared/__init__.py
documente_shared/application/__init__.py
documente_shared/application/dates.py
documente_shared/application/digest.py
documente_shared/application/exceptions.py
documente_shared/application/files.py
documente_shared/application/json.py
documente_shared/application/numbers.py
documente_shared/application/payloads.py
documente_shared/application/query_params.py
documente_shared/application/retry_utils.py
documente_shared/application/time_utils.py
documente_shared/application/timezone.py
documente_shared/domain/__init__.py
documente_shared/domain/base_enum.py
documente_shared/domain/constants.py
documente_shared/domain/entities/__init__.py
documente_shared/domain/entities/document.py
documente_shared/domain/entities/document_metadata.py
documente_shared/domain/entities/in_memory_document.py
documente_shared/domain/entities/processing_case.py
documente_shared/domain/entities/processing_case_filters.py
documente_shared/domain/entities/processing_case_item.py
documente_shared/domain/entities/processing_case_item_filters.py
documente_shared/domain/entities/processing_documents.py
documente_shared/domain/entities/processing_event.py
documente_shared/domain/entities/scaling.py
documente_shared/domain/enums/__init__.py
documente_shared/domain/enums/circular_oficio.py
documente_shared/domain/enums/common.py
documente_shared/domain/enums/document.py
documente_shared/domain/enums/document_type_record.py
documente_shared/domain/enums/processing_case.py
documente_shared/domain/exceptions.py
documente_shared/domain/interfaces/__init__.py
documente_shared/domain/interfaces/scaling.py
documente_shared/domain/repositories/__init__.py
documente_shared/domain/repositories/document.py
documente_shared/domain/repositories/processing_case.py
documente_shared/domain/repositories/processing_case_item.py
documente_shared/infrastructure/__init__.py
documente_shared/infrastructure/documente_client.py
documente_shared/infrastructure/dynamo_table.py
documente_shared-0.1.147.dist-info/METADATA
documente_shared-0.1.147.dist-info/WHEEL
documente_shared-0.1.147.dist-info/RECORD
