Metadata-Version: 2.1
Name: documente_shared
Version: 0.1.147
Summary: Shared utilities for Documente AI projects
License: MIT
Author: Tech
Author-email: tech@llamitai.com
Requires-Python: >=3.10,<3.13
Classifier: License :: OSI Approved :: MIT License
Classifier: Programming Language :: Python :: 3
Classifier: Programming Language :: Python :: 3.10
Classifier: Programming Language :: Python :: 3.11
Classifier: Programming Language :: Python :: 3.12
Requires-Dist: boto3 (>=1.37.19,<2.0.0)
Requires-Dist: botocore (>=1.37.19,<2.0.0)
Requires-Dist: loguru (>=0.7.3,<0.8.0)
Requires-Dist: pytz (>=2025.2,<2026.0)
Requires-Dist: requests (>=2.32.3,<3.0.0)
Requires-Dist: sentry-sdk (>=2.19.2,<3.0.0)
Requires-Dist: unidecode (>=1.3.8,<2.0.0)
